{
    "targets": {
        "swap": {}
    },
    "passes": [
        {
            "vertex_shader": "minecraft:core/screenquad",
            "fragment_shader": "bubbleshield:screenfx/sfx_324",
            "inputs": [
                {
                    "sampler_name": "In",
                    "target": "minecraft:main"
                }
            ],
            "output": "swap",
            "uniforms": {
                "FxConfig": [
                    {
                        "name": "Primary",
                        "type": "vec4",
                        "value": [
                            0.1255,
                            0.549,
                            0.4784,
                            1.0
                        ]
                    },
                    {
                        "name": "Secondary",
                        "type": "vec4",
                        "value": [
                            0.698,
                            0.9059,
                            0.9216,
                            1.0
                        ]
                    },
                    {
                        "name": "ParamsA",
                        "type": "vec4",
                        "value": [
                            4.188,
                            0.93,
                            50.0,
                            0.0
                        ]
                    },
                    {
                        "name": "ParamsB",
                        "type": "vec4",
                        "value": [
                            0.243,
                            1.2056,
                            0.55,
                            0.35
                        ]
                    }
                ]
            }
        },
        {
            "vertex_shader": "minecraft:core/screenquad",
            "fragment_shader": "minecraft:post/blit",
            "inputs": [
                {
                    "sampler_name": "In",
                    "target": "swap"
                }
            ],
            "output": "minecraft:main",
            "uniforms": {
                "BlitConfig": [
                    {
                        "name": "ColorModulate",
                        "type": "vec4",
                        "value": [
                            1.0,
                            1.0,
                            1.0,
                            1.0
                        ]
                    }
                ]
            }
        }
    ]
}
